[
  {
    "date": 1994,
    "value": null
  },
  {
    "date": 1995,
    "value": null
  },
  {
    "date": 1996,
    "value": null
  },
  {
    "date": 1997,
    "value": null
  },
  {
    "date": 1998,
    "value": -3.3846862132337
  },
  {
    "date": 1999,
    "value": -6.1130721498046
  },
  {
    "date": 2000,
    "value": -3.12229518191751
  },
  {
    "date": 2001,
    "value": null
  },
  {
    "date": 2002,
    "value": null
  },
  {
    "date": 2003,
    "value": -5.04967005952806
  },
  {
    "date": 2004,
    "value": null
  },
  {
    "date": 2005,
    "value": null
  },
  {
    "date": 2006,
    "value": null
  },
  {
    "date": 2007,
    "value": null
  },
  {
    "date": 2008,
    "value": -5.72450803056946
  },
  {
    "date": 2009,
    "value": -7.08183877154717
  },
  {
    "date": 2010,
    "value": -4.56011818549425
  },
  {
    "date": 2011,
    "value": -1.07075617545713
  },
  {
    "date": 2012,
    "value": 2.76559285648913
  },
  {
    "date": 2013,
    "value": -5.53469562087851
  },
  {
    "date": 2014,
    "value": -4.16681218983894
  },
  {
    "date": 2015,
    "value": -1.40738619185838
  },
  {
    "date": 2016,
    "value": -3.04286241958897
  },
  {
    "date": 2017,
    "value": -2.19824409588726
  },
  {
    "date": 2018,
    "value": -2.61320674678311
  },
  {
    "date": 2019,
    "value": -2.23798643665382
  },
  {
    "date": 2020,
    "value": -8.51553357908288
  },
  {
    "date": 2021,
    "value": -7.65394474545161
  },
  {
    "date": 2022,
    "value": -5.29929051233517
  },
  {
    "date": 2023,
    "value": -2.04098550110347
  },
  {
    "date": 2024,
    "value": -4.65465157436065
  }
]